gensum/__init__.py
gensum/generator.py
gensum/gensum.py
gensum-0.1.5.dist-info/LICENSE
gensum-0.1.5.dist-info/METADATA
gensum-0.1.5.dist-info/WHEEL
gensum-0.1.5.dist-info/top_level.txt
gensum-0.1.5.dist-info/RECORD
