Metadata-Version: 2.1
Name: gensum
Version: 0.1.5
Summary: Generative Summarization for Data Augmentation
Home-page: https://github.com/aaronbriel/gensum
Author: Aaron Briel
Author-email: aaronbriel@gmail.com
License: Apache License 2.0
License-File: LICENSE
Requires-Dist: numpy
Requires-Dist: pandas
Requires-Dist: openai
